sqlcipher3/__init__.py
sqlcipher3/_sqlite3.cpython-313-x86_64-linux-gnu.so
sqlcipher3/dbapi2.py
sqlcipher3_binary.libs/libcrypto-0dcfa43e.so.3
sqlcipher3_binary-0.6.0.dist-info/METADATA
sqlcipher3_binary-0.6.0.dist-info/WHEEL
sqlcipher3_binary-0.6.0.dist-info/top_level.txt
sqlcipher3_binary-0.6.0.dist-info/RECORD
sqlcipher3_binary-0.6.0.dist-info/licenses/LICENSE
