Metadata-Version: 2.1
Name: sqlcipher3-binary
Version: 0.6.0
Summary: DB-API 2.0 interface for SQLCipher 3.x
Home-page: https://github.com/coleifer/sqlcipher3
Author: Charles Leifer
Author-email: coleifer@gmail.com
License: MIT License
Platform: ALL
Classifier: Development Status :: 4 - Beta
Classifier: Intended Audience :: Developers
Classifier: Operating System :: MacOS :: MacOS X
Classifier: Operating System :: Microsoft :: Windows
Classifier: Operating System :: POSIX
Classifier: Programming Language :: C
Classifier: Programming Language :: Python
Classifier: Topic :: Database :: Database Engines/Servers
Classifier: Topic :: Software Development :: Libraries :: Python Modules
License-File: LICENSE
